xbee_image_transfer/__init__.py
xbee_image_transfer/main.py
xbee_image_transfer-0.0.1.dist-info/LICENSE
xbee_image_transfer-0.0.1.dist-info/METADATA
xbee_image_transfer-0.0.1.dist-info/WHEEL
xbee_image_transfer-0.0.1.dist-info/top_level.txt
xbee_image_transfer-0.0.1.dist-info/RECORD
